pyTuxAPI/__init__.py
pyTuxAPI/api_client.py
pyTuxAPI/utils.py
pyTuxAPI-0.1.0.dist-info/METADATA
pyTuxAPI-0.1.0.dist-info/WHEEL
pyTuxAPI-0.1.0.dist-info/top_level.txt
pyTuxAPI-0.1.0.dist-info/RECORD
